QuizzingPackage/__init__.py
QuizzingPackage/Objects/__init__.py
QuizzingPackage/Objects/question.py
QuizzingPackage/Objects/response.py
QuizzingPackage/Quizzes/__init__.py
QuizzingPackage/Quizzes/marker.py
QuizzingPackage/Quizzes/quiz.py
QuizzingPackage-0.0.1.dist-info/LICENSE.txt
QuizzingPackage-0.0.1.dist-info/METADATA
QuizzingPackage-0.0.1.dist-info/WHEEL
QuizzingPackage-0.0.1.dist-info/top_level.txt
QuizzingPackage-0.0.1.dist-info/RECORD
