Metadata-Version: 2.1
Name: QuizzingPackage
Version: 0.0.1
Summary: An package able to make a quiz.
Author-email: Zetian Zhao <a13317881985@gmail.com>, Haoxiang Xu <lance924852785@gmail.com>
Project-URL: Homepage, https://github.com/skywalker007-cpu/533-QuizzingPackage
Project-URL: Issues, https://github.com/skywalker007-cpu/533-QuizzingPackage/issues
Classifier: Programming Language :: Python :: 3
Classifier: License :: OSI Approved :: MIT License
Classifier: Operating System :: OS Independent
Requires-Python: >=3.9
License-File: LICENSE.txt
